ssh_mcp_server/__init__.py
ssh_mcp_server/auth_cli.py
ssh_mcp_server/credentials.py
ssh_mcp_server/server.py
ssh_mcp_server-0.1.1.dist-info/LICENSE
ssh_mcp_server-0.1.1.dist-info/METADATA
ssh_mcp_server-0.1.1.dist-info/WHEEL
ssh_mcp_server-0.1.1.dist-info/entry_points.txt
ssh_mcp_server-0.1.1.dist-info/top_level.txt
ssh_mcp_server-0.1.1.dist-info/RECORD
