Metadata-Version: 2.1
Name: ssh-mcp-server
Version: 0.1.1
Summary: MCP server providing SSH client functionality for remote Linux server management
Author-email: Rory McMahon <rory.mcmahon@vocus.com.au>
License: MIT
Project-URL: Homepage, https://github.com/rorymcmahon/ssh-mcp-server
Project-URL: Repository, https://github.com/rorymcmahon/ssh-mcp-server
Project-URL: Issues, https://github.com/rorymcmahon/ssh-mcp-server/issues
Classifier: Development Status :: 3 - Alpha
Classifier: Intended Audience :: Developers
Classifier: License :: OSI Approved :: MIT License
Classifier: Programming Language :: Python :: 3
Classifier: Programming Language :: Python :: 3.8
Classifier: Programming Language :: Python :: 3.9
Classifier: Programming Language :: Python :: 3.10
Classifier: Programming Language :: Python :: 3.11
Classifier: Programming Language :: Python :: 3.12
Requires-Python: >=3.8
License-File: LICENSE
Requires-Dist: mcp==1.14.1
Requires-Dist: paramiko==4.0.0
Provides-Extra: dev
Requires-Dist: pytest>=7.0.0; extra == "dev"
Requires-Dist: pytest-asyncio>=0.21.0; extra == "dev"
Requires-Dist: pytest-cov>=4.0.0; extra == "dev"
Requires-Dist: black>=23.0.0; extra == "dev"
Requires-Dist: isort>=5.12.0; extra == "dev"
Requires-Dist: flake8>=6.0.0; extra == "dev"
Requires-Dist: mypy>=1.0.0; extra == "dev"
Provides-Extra: security
Requires-Dist: safety>=3.0.0; extra == "security"
Requires-Dist: pip-audit>=2.6.0; extra == "security"
